pyparsedvd/__init__.py
pyparsedvd/py.typed
pyparsedvd/sector.py
pyparsedvd/vts_ifo/__init__.py
pyparsedvd/vts_ifo/load.py
pyparsedvd/vts_ifo/sector_offsets.py
pyparsedvd/vts_ifo/vts_pgci.py
pyparsedvd-0.0.3.dist-info/LICENSE
pyparsedvd-0.0.3.dist-info/METADATA
pyparsedvd-0.0.3.dist-info/WHEEL
pyparsedvd-0.0.3.dist-info/top_level.txt
pyparsedvd-0.0.3.dist-info/RECORD
