Metadata-Version: 2.1
Name: pyparsedvd
Version: 0.0.3
Summary: Parse and extract binary data from dvd files
Home-page: https://github.com/Ichunjo/pyparsedvd
Author: Vardë
Author-email: ichunjo.le.terrible@gmail.com
License: UNKNOWN
Platform: UNKNOWN
Classifier: Intended Audience :: Developers
Classifier: Programming Language :: Python :: 3
Classifier: License :: OSI Approved :: MIT License
Classifier: Operating System :: OS Independent
Requires-Python: >=3.9
